pyrep/Repository.py
pyrep/__init__.py
pyrep/__pkginfo__.py
pyrep/test.py
pyrep-3.2.0.dist-info/LICENSE.txt
pyrep-3.2.0.dist-info/METADATA
pyrep-3.2.0.dist-info/WHEEL
pyrep-3.2.0.dist-info/top_level.txt
pyrep-3.2.0.dist-info/RECORD
